Metadata-Version: 1.0
Name: distributionsGAC
Version: 0.1
Summary: Gaussian and Binomial distributions
Home-page: UNKNOWN
Author: Gema Atienza Chercoles
Author-email: UNKNOWN
License: UNKNOWN
Platform: UNKNOWN
